matplotlib_arm64-3.3.4-py3.6-nspkg.pth
pylab.py
mpl_toolkits/axes_grid1/inset_locator.py
mpl_toolkits/axes_grid1/colorbar.py
mpl_toolkits/axes_grid1/mpl_axes.py
mpl_toolkits/axes_grid1/parasite_axes.py
mpl_toolkits/axes_grid1/__init__.py
mpl_toolkits/axes_grid1/anchored_artists.py
mpl_toolkits/axes_grid1/axes_size.py
mpl_toolkits/axes_grid1/axes_rgb.py
mpl_toolkits/axes_grid1/axes_divider.py
mpl_toolkits/axes_grid1/axes_grid.py
mpl_toolkits/mplot3d/proj3d.py
mpl_toolkits/mplot3d/__init__.py
mpl_toolkits/mplot3d/art3d.py
mpl_toolkits/mplot3d/axis3d.py
mpl_toolkits/mplot3d/axes3d.py
mpl_toolkits/axes_grid/inset_locator.py
mpl_toolkits/axes_grid/colorbar.py
mpl_toolkits/axes_grid/grid_helper_curvelinear.py
mpl_toolkits/axes_grid/grid_finder.py
mpl_toolkits/axes_grid/parasite_axes.py
mpl_toolkits/axes_grid/__init__.py
mpl_toolkits/axes_grid/clip_path.py
mpl_toolkits/axes_grid/anchored_artists.py
mpl_toolkits/axes_grid/axislines.py
mpl_toolkits/axes_grid/floating_axes.py
mpl_toolkits/axes_grid/axis_artist.py
mpl_toolkits/axes_grid/angle_helper.py
mpl_toolkits/axes_grid/axes_size.py
mpl_toolkits/axes_grid/axes_rgb.py
mpl_toolkits/axes_grid/axes_divider.py
mpl_toolkits/axes_grid/axes_grid.py
mpl_toolkits/axes_grid/axisline_style.py
mpl_toolkits/axisartist/grid_helper_curvelinear.py
mpl_toolkits/axisartist/grid_finder.py
mpl_toolkits/axisartist/parasite_axes.py
mpl_toolkits/axisartist/__init__.py
mpl_toolkits/axisartist/clip_path.py
mpl_toolkits/axisartist/axislines.py
mpl_toolkits/axisartist/floating_axes.py
mpl_toolkits/axisartist/axis_artist.py
mpl_toolkits/axisartist/angle_helper.py
mpl_toolkits/axisartist/axes_rgb.py
mpl_toolkits/axisartist/axes_divider.py
mpl_toolkits/axisartist/axes_grid.py
mpl_toolkits/axisartist/axisline_style.py
mpl_toolkits/tests/test_axisartist_clip_path.py
mpl_toolkits/tests/test_axisartist_axislines.py
mpl_toolkits/tests/test_axisartist_floating_axes.py
matplotlib_arm64-3.3.4.dist-info/WHEEL
matplotlib_arm64-3.3.4.dist-info/RECORD
matplotlib_arm64-3.3.4.dist-info/METADATA
matplotlib_arm64-3.3.4.dist-info/top_level.txt
matplotlib_arm64-3.3.4.dist-info/namespace_packages.txt
