Metadata-Version: 2.1
Name: matplotlib-arm64
Version: 3.3.4
Summary: Python plotting package
Home-page: https://matplotlib.org
Author: John D. Hunter, Michael Droettboom
Author-email: matplotlib-users@python.org
License: PSF
Download-URL: https://matplotlib.org/users/installing.html
Project-URL: Documentation, https://matplotlib.org
Project-URL: Source Code, https://github.com/matplotlib/matplotlib
Project-URL: Bug Tracker, https://github.com/matplotlib/matplotlib/issues
Project-URL: Forum, https://discourse.matplotlib.org/
Project-URL: Donate, https://numfocus.org/donate-to-matplotlib
Platform: any
Classifier: Development Status :: 5 - Production/Stable
Classifier: Framework :: Matplotlib
Classifier: Intended Audience :: Science/Research
Classifier: Intended Audience :: Education
Classifier: License :: OSI Approved :: Python Software Foundation License
Classifier: Programming Language :: Python
Classifier: Programming Language :: Python :: 3
Classifier: Programming Language :: Python :: 3.6
Classifier: Programming Language :: Python :: 3.7
Classifier: Programming Language :: Python :: 3.8
Classifier: Topic :: Scientific/Engineering :: Visualization
Requires-Python: >=3.6
Requires-Dist: cycler (>=0.10)
Requires-Dist: kiwisolver (>=1.0.1)
Requires-Dist: numpy (>=1.15)
Requires-Dist: pillow (>=6.2.0)
Requires-Dist: pyparsing (!=2.0.4,!=2.1.2,!=2.1.6,>=2.0.3)
Requires-Dist: python-dateutil (>=2.1)
